{
  "number": 652,
  "slug": "orv-seq-ch-652",
  "title": "652 Episode 19 People of the Past (4)",
  "order": 652,
  "segments": [
    {
      "kind": "line",
      "text": "I stared at the door created at the end of the waiting room."
    },
    {
      "kind": "line",
      "text": "There was only one door when there should have been seven."
    },
    {
      "kind": "line",
      "text": "Is this the original progression of the 41st round of Ways of Survival, or is it because something has changed as I and the readers intervened?"
    },
    {
      "kind": "line",
      "text": "If it was the original development of 'Ways of Survival', it was normal for the 'Ways of Survival' skill to activate at this point. However, the 'Ways of Survival' skill was quiet."
    },
    {
      "kind": "line",
      "text": "That means that the readers intervened and the scenario changed."
    },
    {
      "kind": "quote",
      "text": "「Someone deliberately changed the plot.」"
    },
    {
      "kind": "line",
      "text": "But did the readers I know carelessly intervene in the scenario?"
    },
    {
      "kind": "line",
      "text": "Dansu ahjussi, Kyung Sein, Ye Hyunwoo, Killer King, Literature Girl, Koo Seonah, Kim Kyungsik."
    },
    {
      "kind": "line",
      "text": "Calmly recalling the list, it never occurred to me that any of them might have been involved in the cataclysm of the scenario."
    },
    {
      "kind": "line",
      "text": "What readers are ahead of the characters is 'information', and they will not try to change the future too much in order to actively utilize the development of the original story."
    },
    {
      "kind": "line",
      "text": "In other words, the readers are not the culprits."
    },
    {
      "kind": "line",
      "text": "If so, who changed the scenario and caused the event of ‘the' collapse of the museum' that did not exist in the original story?"
    },
    {
      "kind": "line",
      "text": "I made a hypothesis."
    },
    {
      "kind": "quote",
      "text": "「Somewhere in this world, if there are people who don’t want the development of the scenario to go the way it was written.」"
    },
    {
      "kind": "line",
      "text": "What if there are people who are at a disadvantage as time goes by when following the development of 'Omniscient Reader'?"
    },
    {
      "kind": "line",
      "text": "Once the hypothesis was established, it felt like the outline of the culprit became clearer."
    },
    {
      "kind": "line",
      "text": "But it wasn't quite yet certain."
    },
    {
      "kind": "line",
      "text": "\"Ahjussi.\""
    },
    {
      "kind": "line",
      "text": "With a trembling voice, Shin Yoosoung joined me."
    },
    {
      "kind": "line",
      "text": "There were so many corpses on the floor of the waiting room that there was no place to step on."
    },
    {
      "kind": "line",
      "text": "It seemed that a fight had already taken place."
    },
    {
      "kind": "line",
      "text": "I wrapped my arms around Shin Yoosoung’s shoulders and walked forward cautiously. I didn't forget to look at the faces of the people around me. I was afraid that there might be a face I knew among them."
    },
    {
      "kind": "line",
      "text": "Dansu ahjussi."
    },
    {
      "kind": "line",
      "text": "Kim Kyungsik and Koo Seonah."
    },
    {
      "kind": "line",
      "text": "And someone I don't know who they possessed, my editor."
    },
    {
      "kind": "line",
      "text": "In an instant, the back of my neck went cold."
    },
    {
      "kind": "line",
      "text": "Reflexively, I bent down and wrapped my arms around Shin Yoosoung."
    },
    {
      "kind": "line",
      "text": "Three daggers grazed my neck and flew to the other side of the waiting room."
    },
    {
      "kind": "line",
      "text": "When I narrowed my eyes, I saw assassins rising among the corpses."
    },
    {
      "kind": "line",
      "text": "\"Jet, did you miss it?\""
    },
    {
      "kind": "line",
      "text": "They were new hunters."
    },
    {
      "kind": "line",
      "text": "Instead of entering the dungeon, they hid in the waiting room and killed new recruits."
    },
    {
      "kind": "line",
      "text": "There were people similar in 'Omniscient Reader'."
    },
    {
      "kind": "line",
      "text": "Hiding Shin Yoosoung behind me, I activated the tale of the Beggar Sect."
    },
    {
      "kind": "line",
      "text": "[Story, the tenacious Murim master' stutters.]"
    },
    {
      "kind": "line",
      "text": "The spirit of the master of Murim rose sharply, and the number of enemies hidden among the corpses were transmitted through my skin."
    },
    {
      "kind": "line",
      "text": "A number over twenty."
    },
    {
      "kind": "line",
      "text": "It was a level of troops that could be called a 'small group'."
    },
    {
      "kind": "line",
      "text": "\"Hmm? That kid…\""
    },
    {
      "kind": "line",
      "text": "I could see some of them exchanging whispers, as if they recognized Shin Yoosoung."
    },
    {
      "kind": "line",
      "text": "I asked Shin Yoosoung in a small voice."
    },
    {
      "kind": "line",
      "text": "\"Are they people you know?\""
    },
    {
      "kind": "line",
      "text": "\"Yes.\""
    },
    {
      "kind": "line",
      "text": "A small tremor came from Shin Yoosoung, who grabbed my sleeve."
    },
    {
      "kind": "line",
      "text": "I asked again."
    },
    {
      "kind": "line",
      "text": "\"Looks like people you don’t want to know anymore.\""
    },
    {
      "kind": "line",
      "text": "The answer came back after a while."
    },
    {
      "kind": "line",
      "text": "\"....Yes.\""
    },
    {
      "kind": "line",
      "text": "I changed 'thought' to 'Broken Faith' in preparation for an emergency."
    },
    {
      "kind": "line",
      "text": "Meanwhile, the assassins exchanged opinions quickly."
    },
    {
      "kind": "line",
      "text": "\"Could it be that you went through that series of battles alone?\""
    },
    {
      "kind": "line",
      "text": "\"Didn’t I tell you? These days, kids are more toxic.\""
    },
    {
      "kind": "line",
      "text": "Right."
    },
    {
      "kind": "line",
      "text": "These people were the adults of the 'union' that tried to put Shin Yoosoung in the group."
    },
    {
      "kind": "line",
      "text": "One of the assassins, who had been watching us closely, came forward with a dagger."
    },
    {
      "kind": "line",
      "text": "\"You. Do you have a group?\""
    },
    {
      "kind": "line",
      "text": "\"I do.\""
    },
    {
      "kind": "line",
      "text": "To say that I have no group here would only make me be looked down on by them."
    },
    {
      "kind": "line",
      "text": "However, even when I said that I had a group, they didn't seem to care."
    },
    {
      "kind": "line",
      "text": "\"You came here by yourself when you have a group?\""
    },
    {
      "kind": "line",
      "text": "\"I am confident in my skills.\""
    },
    {
      "kind": "line",
      "text": "It was a provocative answer, but several assassins unexpectedly nodded."
    },
    {
      "kind": "line",
      "text": "\"If you came over with a kid, there's a high possibility that you're from a one-person dungeon.\""
    },
    {
      "kind": "line",
      "text": "\"The single-person dungeon difficulty is more difficult.\""
    },
    {
      "kind": "line",
      "text": "\"It's worth having as an ally.\""
    },
    {
      "kind": "line",
      "text": "The Assassin Leader, who quickly gathered opinions, nodded."
    },
    {
      "kind": "line",
      "text": "\"We respect talented people. Please leave your group and move on to this group.\""
    },
    {
      "kind": "line",
      "text": "Suddenly, Shin Yoosoung's words came to mind. If 'union' is unconditionally skill-first, this…"
    },
    {
      "kind": "line",
      "text": "\"I'll accept both you and her. It looks like you've developed a special relationship.\""
    },
    {
      "kind": "line",
      "text": "Speech that seems to be condescending."
    },
    {
      "kind": "line",
      "text": "I glared at him with my eyes narrowed."
    },
    {
      "kind": "line",
      "text": "[The exclusive skill 'Character List' is activated!]"
    },
    {
      "kind": "line",
      "text": "First of all, it is not a 'reader'."
    },
    {
      "kind": "window",
      "text": "Name: Perjury\nAge: 35\nConstellation support: Legendary Assassin\nExclusive Attribute: Assassin (Normal)\nExclusive Skills: [Ambush Lv.3], [Gidobinic Lv.3], [Weapon Improvement Lv.2]\nStigma: [Scheduled Special Lv.1], [Silver Bullet Lv.2], [Shadow Stealth Lv.2]\nOverall stats: [Health Lv. 20], [Strength Lv.25], [Agility Lv.25], [Magic Power Lv.21]\nComprehensive evaluation: It is an incarnation of the union. He is active as one of the 7 kings of Seoul."
    },
    {
      "kind": "line",
      "text": "He was the first person I saw. He must have been one of the extras in 'Ways of Survival'."
    },
    {
      "kind": "line",
      "text": "His supportive Constellation is..."
    },
    {
      "kind": "line",
      "text": "...Legendary Assassin."
    },
    {
      "kind": "line",
      "text": "It was a constellation that had never appeared in 'Omniscient Reader'."
    },
    {
      "kind": "line",
      "text": "[Exclusive skill 'Three ways to survive in a ruined world' is activated!]"
    },
    {
      "kind": "line",
      "text": "Fortunately, the 'Ways of Survival' skill was activated in time."
    },
    {
      "kind": "quote",
      "text": "「Legendary Assassin, the modifier is grandiose, but among those who have become constellations, there is no Constellation without Legend. In other words, it's an ordinary historical-grade constellation.」"
    },
    {
      "kind": "line",
      "text": "Huh. Right."
    },
    {
      "kind": "quote",
      "text": "「This is a sponsor that is common among assassins, and like the 'lord of mischief', random incarnations are sprinkled with background selection and then reaped as assassins. They often lend their grown incarnations to other constellations as mercenaries.」"
    },
    {
      "kind": "line",
      "text": "I know who his sponsor is."
    },
    {
      "kind": "line",
      "text": "I was thinking of saving myself a bit if there was an Myth-grade constellation behind him, but I think I can go out strong with this level."
    },
    {
      "kind": "line",
      "text": "\"I'm sorry, but I have no intention of joining your group.\""
    },
    {
      "kind": "line",
      "text": "\"Even though we're a group of 'Seoul Gwang'? You've probably heard of the union, right?\""
    },
    {
      "kind": "line",
      "text": "The union."
    },
    {
      "kind": "line",
      "text": "Could it be that the group that Ye Hyunwoo was talking about were these guys?"
    },
    {
      "kind": "line",
      "text": "I nodded and asked."
    },
    {
      "kind": "line",
      "text": "\"This is where the Tyrant King resides, right?\""
    },
    {
      "kind": "line",
      "text": "The man who subtly frowned at the name of the Tyrant King said."
    },
    {
      "kind": "line",
      "text": "\"We are under the command of the 'Assassin King'.\""
    },
    {
      "kind": "line",
      "text": "Assassin King?"
    },
    {
      "kind": "line",
      "text": "There is no such name among the 7 kings of Seoul I know."
    },
    {
      "kind": "line",
      "text": "\"You don't seem to know how big of an opportunity this is, but we will soon retrieve the 'Sword of Death' and obtain the 'Absolute Throne'. I don't know where your group is, but at this point there are no forces greater than ours. You’d better make a wise choice.\""
    },
    {
      "kind": "line",
      "text": "I replied with a dry nod."
    },
    {
      "kind": "line",
      "text": "\"I hear you. But it doesn't go below that. I have no intention of fighting, so please pass on your troops.\""
    },
    {
      "kind": "line",
      "text": "It was half sincere."
    },
    {
      "kind": "line",
      "text": "There was a bit of fatigue left after passing through the 'Field of Nagak', and even if it were me, it was not easy to subdue twenty assassins without a single wound. And above all,"
    },
    {
      "kind": "quote",
      "text": "「I didn't want to kill people if possible.」"
    },
    {
      "kind": "line",
      "text": "Even if I control myself with [Incite], there is a limit. Killing people for whatever reason is never a pleasant experience."
    },
    {
      "kind": "line",
      "text": "The reason why Kim Dokja at the beginning of Omniscient Reader chose to become the 'King of no killing' seemed to be understood a little now."
    },
    {
      "kind": "line",
      "text": "Of course, the assassin who didn't even know who Kim Dokja was wasn't going to listen to me."
    },
    {
      "kind": "line",
      "text": "\"Then die here.\""
    },
    {
      "kind": "line",
      "text": "I smiled with my eyes wide open."
    },
    {
      "kind": "line",
      "text": "\"No compromise? Aren't we members of society?\""
    },
    {
      "kind": "line",
      "text": "\"Society has already perished.\""
    },
    {
      "kind": "line",
      "text": "I don't know who is in charge of the alliance, but why did they make all the members of the group look like Kim Namwoon?"
    },
    {
      "kind": "line",
      "text": "\"I’m still a member of society.\""
    },
    {
      "kind": "line",
      "text": "\"Then die as a member of society.\""
    },
    {
      "kind": "line",
      "text": "It can't be."
    },
    {
      "kind": "line",
      "text": "I made a quick calculation in my head."
    },
    {
      "kind": "line",
      "text": "Should I use [Incite]?"
    },
    {
      "kind": "line",
      "text": "Or, should I start by eliminating that guy with the 'Blade of Faith'?"
    },
    {
      "kind": "line",
      "text": "As I secretly tried to carry out a strategy with a way to wipe out these people at once without hurting Shin Yoosoung, Shin Yoosoung pulled my sleeves."
    },
    {
      "kind": "line",
      "text": "\"Ahjussi.\""
    },
    {
      "kind": "line",
      "text": "Looking back, Shin Yoosoung's eyes shimmered with golden energy. My head throbbed, and a sense of dizziness passed through my head."
    },
    {
      "kind": "line",
      "text": "I think something similar happened before."
    },
    {
      "kind": "line",
      "text": "\"I'll just finish it.\""
    },
    {
      "kind": "line",
      "text": "Why? At that moment, Shin Yoosoung seemed like a completely different person from the Shin Yoosoung I knew."
    },
    {
      "kind": "line",
      "text": "\"Finish it... how?\""
    },
    {
      "kind": "line",
      "text": "\"Therefore…\""
    },
    {
      "kind": "line",
      "text": "It was then that a roar rang out from inside the waiting room."
    },
    {
      "kind": "line",
      "text": "\"Get out of the way!\""
    },
    {
      "kind": "line",
      "text": "Suddenly, the door to the waiting room opened. A crowd poured out."
    },
    {
      "kind": "line",
      "text": "\"What…\""
    },
    {
      "kind": "line",
      "text": "With a booming sound, the assassin's head shattered. The astonished assassins screamed."
    },
    {
      "kind": "line",
      "text": "\"What, what is it?\""
    },
    {
      "kind": "line",
      "text": "The assassins wandered around and raised their swords."
    },
    {
      "kind": "line",
      "text": "But whenever the sound of wind was heard in the air, the number of assassins was steadily decreasing. The awe-inspiring assassins clung to the walls and shouted loudly."
    },
    {
      "kind": "line",
      "text": "\"Who! Who dares-\""
    },
    {
      "kind": "line",
      "text": "A series of group members appeared through the pouring pit."
    },
    {
      "kind": "line",
      "text": "Leading the group members was a giant."
    },
    {
      "kind": "line",
      "text": "There was an iron pipe embracing the dazzling light of the giant's fish, and at a glance it was an S-class item."
    },
    {
      "kind": "line",
      "text": "\"King of gangsters!\""
    },
    {
      "kind": "line",
      "text": "King of gangsters?"
    },
    {
      "kind": "line",
      "text": "No matter how much I searched in my head, there was no king with such a nickname."
    },
    {
      "kind": "quote",
      "text": "「A person who did not appear in Omniscient Reader’s Viewpoint.」"
    },
    {
      "kind": "line",
      "text": "I was nervous and watched the development of the situation. Looking closely, the wind was blowing from the right side of the group."
    },
    {
      "kind": "line",
      "text": "Four kitchen knives that moved in a zigzag pattern cut through the air."
    },
    {
      "kind": "line",
      "text": "\"Ah! Heartless Mother!\""
    },
    {
      "kind": "line",
      "text": "Heartless Mother. This was also the first time I had ever heard this nickname. A dazzling passing technique performed by a mother and daughter each holding a pair of kitchen knives. It was a terrifying sight just to look at from a distance."
    },
    {
      "kind": "line",
      "text": "However… What?"
    },
    {
      "kind": "line",
      "text": "I was used to the mother and daughter's faces."
    },
    {
      "kind": "line",
      "text": "“Inhopa group! Inhopa is back!\""
    },
    {
      "kind": "line",
      "text": "Inhopa?"
    },
    {
      "kind": "line",
      "text": "\"Aaaaaaaaaaaaaaaaaaaaa-\""
    },
    {
      "kind": "line",
      "text": "A few terrified assassins tried to run screaming into the dungeon, but their lives were lost."
    },
    {
      "kind": "line",
      "text": "Now, the number of assassins left in the waiting room was less than five."
    },
    {
      "kind": "line",
      "text": "The assassin who was threatening me earlier growled."
    },
    {
      "kind": "line",
      "text": "\"King of gangsters! We are an alliance. Do you think you'll be safe after doing this to us?\""
    },
    {
      "kind": "line",
      "text": "\"If you all die, who will know what I did?\""
    },
    {
      "kind": "line",
      "text": "\"Ooh, there are those who watched us suffer.\""
    },
    {
      "kind": "line",
      "text": "Then, the gangster king's party looked around the edge of the waiting room."
    },
    {
      "kind": "line",
      "text": "Some of the incarnations who watched the situation with a bonfire were there."
    },
    {
      "kind": "line",
      "text": "\"Are you going to tell about it?\""
    },
    {
      "kind": "line",
      "text": "The incarnations all shook their heads at the gangster king's despair."
    },
    {
      "kind": "line",
      "text": "\"We didn't see anything.\""
    },
    {
      "kind": "line",
      "text": "\"Yes, you guys-\""
    },
    {
      "kind": "line",
      "text": "Before the bewildered assassin could shout anything, an iron pipe shattered his head."
    },
    {
      "kind": "line",
      "text": "Watching the assassin collapse powerlessly, the king of gangsters spat out curse words."
    },
    {
      "kind": "line",
      "text": "\"Eh, wicked bastards.\""
    },
    {
      "kind": "line",
      "text": "\"Looking at it, it seems that he was persecuting newcomers again.\""
    },
    {
      "kind": "line",
      "text": "\"Anyway, that's what all the alliance scum do.\""
    },
    {
      "kind": "line",
      "text": "I was honestly surprised. Anyway, I heard that the 'Union' is the strongest force at the moment."
    },
    {
      "kind": "line",
      "text": "But is there a rebel group that fights against the alliance with only a single force?"
    },
    {
      "kind": "line",
      "text": "I saw the gangster king who spotted us and was approaching us."
    },
    {
      "kind": "line",
      "text": "\"Boss, are you okay?\""
    },
    {
      "kind": "line",
      "text": "It was difficult to immediately recognize his face as it was soaked in blood, but the man's long, rough, all-back hair caught my eye immediately."
    },
    {
      "kind": "line",
      "text": "When I saw it up close, I laughed out loud."
    },
    {
      "kind": "line",
      "text": "No wonder. So, was it Inhopa?"
    },
    {
      "kind": "line",
      "text": "\"Uh?\""
    },
    {
      "kind": "line",
      "text": "The gangster king, who had approached us, opened his eyes wide at me. I was wrong in my guess that he was a person who did not appear in the 'Omniscient Reader'."
    },
    {
      "kind": "line",
      "text": "Because the man was someone I already knew."
    },
    {
      "kind": "line",
      "text": "A person who changed the scenario but is neither a reader nor a member of the Misreading association."
    },
    {
      "kind": "line",
      "text": "In 'Omniscient Reader', he was just an extra villain, let alone a king, and a man who died tragically as a petty gangster."
    },
    {
      "kind": "line",
      "text": "\"It’s you, bro?\""
    },
    {
      "kind": "line",
      "text": "I nodded and replied."
    },
    {
      "kind": "line",
      "text": "\"Bang Cheolsoo.\""
    },
    {
      "kind": "line",
      "text": "The action leader of Geumho Station."
    },
    {
      "kind": "line",
      "text": "[The constellation 'Lord of Mischief' welcomes you.]"
    },
    {
      "kind": "line",
      "text": "People who knew me came running to welcome me. Incarnations of Geumho Station, including Dayoung and Dayoung's mother."
    },
    {
      "kind": "line",
      "text": "Those who had killed each other for their own safety now formed a group to help the weak."
    },
    {
      "kind": "line",
      "text": "Once again, I realized that this story is not the 'Omniscient Reader’s Viewpoint' that I knew."
    },
    {
      "kind": "line",
      "text": "[A new loss is recorded on the 'last wall'.]"
    },
    {
      "kind": "line",
      "text": "Shin Yoosoung, who was standing next to me, was looking at the same scenery with blank eyes."
    },
    {
      "kind": "line",
      "text": "\"Brother! Uuuuuuuuu! You’re alive!\""
    },
    {
      "kind": "line",
      "text": "\"Inho ahjussi.\""
    },
    {
      "kind": "line",
      "text": "Looking at Dayoung and her mother waving their hands and people shouting at me, I thought about the story."
    },
    {
      "kind": "line",
      "text": "\"Do you know how much we found!\""
    },
    {
      "kind": "line",
      "text": "I no longer believe that stories can keep world peace like my parents said."
    },
    {
      "kind": "line",
      "text": "No matter how many funny stories there are in the world, people will still start a war and hate someone."
    },
    {
      "kind": "line",
      "text": "But, nonetheless, I continue to think."
    },
    {
      "kind": "line",
      "text": "[The constellation 'Demon-like Judge of Fire' nods.]"
    },
    {
      "kind": "line",
      "text": "[The constellation 'Prisoner of the Golden Headband' sometimes says that this kind of story isn't bad.]"
    },
    {
      "kind": "line",
      "text": "[The constellation 'Abyssal Black Flame Dragon' agrees with his lips twitching.]"
    },
    {
      "kind": "line",
      "text": "Because at least someone reads the story and changes."
    },
    {
      "kind": "line",
      "text": "[The losses you recorded will come to fruition.]"
    },
    {
      "kind": "line",
      "text": "[You acquired a new attribute!]"
    }
  ],
  "authorNote": [],
  "sourceUrl": "epub:orv_sequel.epub#100",
  "scrapedAt": "2026-04-20T21:23:47.500Z"
}
