{
  "number": 666,
  "slug": "orv-seq-ch-666",
  "title": "666 Episode 21 Kim Dokja (2)",
  "order": 666,
  "segments": [
    {
      "kind": "line",
      "text": "[You have hunted a 'Disaster' for the first time in the scenario.]"
    },
    {
      "kind": "line",
      "text": "[You have achieved something no one else has achieved.]"
    },
    {
      "kind": "line",
      "text": "[Payment of compensation related to the scenario is being delayed.]"
    },
    {
      "kind": "line",
      "text": "[Payment of core rewards is determined based on contribution.]"
    },
    {
      "kind": "line",
      "text": "[10,000 coins were obtained.]"
    },
    {
      "kind": "line",
      "text": "Killer King, Ja Yerin, Lee Dansu, and the others looked blankly at the messages pouring out of the air."
    },
    {
      "kind": "line",
      "text": "[The reward for defeating 'Labyrinth Sentinel' has been obtained.]"
    },
    {
      "kind": "line",
      "text": "[You have won 10,000 coins.]"
    },
    {
      "kind": "line",
      "text": "[You have achieved a non-existent achievement!]"
    },
    {
      "kind": "line",
      "text": "[Many constellations admire your achievements!]"
    },
    {
      "kind": "line",
      "text": "[Someone recommended your story to the <Star Stream>]"
    },
    {
      "kind": "line",
      "text": "In only the fourth scenario, they achieved the feat of defeating both level 5 and level 6 species."
    },
    {
      "kind": "line",
      "text": "Each person's contribution was different, but the reward was greater than any other scenario so far."
    },
    {
      "kind": "line",
      "text": "But no one in the group was happy about that."
    },
    {
      "kind": "line",
      "text": "\"What is Cheon Inho’s condition?\""
    },
    {
      "kind": "line",
      "text": "\"Not good.\""
    },
    {
      "kind": "line",
      "text": "Yerin, who had taken a look at Cheon Inho, shook her head."
    },
    {
      "kind": "line",
      "text": "Killer King looked down at Cheon Inho, who was still unconscious, and saw the poisonous dragon species fall."
    },
    {
      "kind": "line",
      "text": "He recalled the last moments."
    },
    {
      "kind": "line",
      "text": "\"If it weren’t for this guy, everyone would have died.\""
    },
    {
      "kind": "line",
      "text": "He could never have imagined that Cheon Inho would appear there. With a body that didn't even seem to have regained consciousness, Cheon Inho ran straight towards the dragon and ripped out its heart."
    },
    {
      "kind": "line",
      "text": "If it weren't for the woman who is taking care of Cheon Inho on the floor right now, Cheon Inho would have died."
    },
    {
      "kind": "line",
      "text": "Cheon Inho's face, poisoned by the poison of the poisonous dragon species, was the color of earth."
    },
    {
      "kind": "line",
      "text": "\"Do you have any medicine?\""
    },
    {
      "kind": "line",
      "text": "In order to neutralize Cheon Inho's poison, the party shook out all the elixirs they had. Although it was not a summoning level elixir, it was still a high quality medicine."
    },
    {
      "kind": "line",
      "text": "In addition, the core of the 'venomous dragon species' that just died."
    },
    {
      "kind": "line",
      "text": "The woman gathered her medicinal herbs, poured them into Cheon Inho's mouth, and cast a strange spell."
    },
    {
      "kind": "line",
      "text": "After a while, something like a small gold frame appeared on Cheon Inho's head, and his complexion began to improve."
    },
    {
      "kind": "line",
      "text": "Killer King asked."
    },
    {
      "kind": "line",
      "text": "\"Do you know Cheon Inho?\""
    },
    {
      "kind": "line",
      "text": "\"Yes.\""
    },
    {
      "kind": "line",
      "text": "\"Right.\""
    },
    {
      "kind": "line",
      "text": "The woman who suddenly appeared was not only the person who saved Cheon Inho, but said that she knew Cheon Inho."
    },
    {
      "kind": "line",
      "text": "Even though the situation was sufficiently strange to raise suspicion, Killer King did not bother to question it."
    },
    {
      "kind": "line",
      "text": "Because there were more urgent problems than that right now."
    },
    {
      "kind": "line",
      "text": "[The final king's qualifications will soon begin.]"
    },
    {
      "kind": "line",
      "text": "Qualifications of the last king."
    },
    {
      "kind": "line",
      "text": "The main stage of 'Battle for the Throne' was finally upon them."
    },
    {
      "kind": "line",
      "text": "\"We need the Death Sword.\""
    },
    {
      "kind": "line",
      "text": "'Death Sword' that can only be obtained by collecting seven star jewels."
    },
    {
      "kind": "line",
      "text": "Coincidentally, all seven jewels were gathered here now."
    },
    {
      "kind": "line",
      "text": "The problem is that, unlike the original story, the person who collects seven jewels is swept away by [madness] and becomes a monster."
    },
    {
      "kind": "line",
      "text": "Ja Yerin said as if holding back."
    },
    {
      "kind": "line",
      "text": "\"It’s still dangerous. \"I don’t know what will happen if he absorbs all seven star gems.\""
    },
    {
      "kind": "line",
      "text": "\"I guess so.\""
    },
    {
      "kind": "line",
      "text": "Killer King looked down at the fallen Cheon Inho for a moment."
    },
    {
      "kind": "line",
      "text": "Cheon Inho risked his life to save them. But will he use Cheon Inho as a sacrifice to obtain the 'Death Sword'?"
    },
    {
      "kind": "line",
      "text": "\"Yoo Joonghyuk doesn’t do such cowardly things.\""
    },
    {
      "kind": "line",
      "text": "Lee Dansu sighed in relief, and Ja Yerin, who looked nervous, also stepped away."
    },
    {
      "kind": "line",
      "text": "But the crisis started now."
    },
    {
      "kind": "line",
      "text": "[The Last King's Qualifications begins.]"
    },
    {
      "kind": "line",
      "text": "Killer King's expression hardened at the message coming from the air."
    },
    {
      "kind": "line",
      "text": "\"It has begun.\""
    },
    {
      "kind": "line",
      "text": "The stage for 'Last Qualifications' had already opened."
    },
    {
      "kind": "line",
      "text": "Killer King looked back at Lee Dansu and said."
    },
    {
      "kind": "line",
      "text": "\"I’m leaving without the Death Sword. All we have to do is somehow block Yoo Joonghyuk.\""
    },
    {
      "kind": "line",
      "text": "Behind the destruction of the 41st round of the original story was the ‘absolute throne'."
    },
    {
      "kind": "line",
      "text": "\"It would be the best if we could destroy the throne with the Death Sword, but even if it’s not the best, there’s no need to despair.\""
    },
    {
      "kind": "line",
      "text": "Even if they don't have the Death Sword, all they have to do is prevent anyone from taking the 'absolute throne'."
    },
    {
      "kind": "line",
      "text": "\"We just have to hold out until the scenario changes. It prevents anyone from sitting on the throne.\""
    },
    {
      "kind": "line",
      "text": "Is the <Star Stream> looking for fun? There is a tendency to move towards more 'plausible' stories."
    },
    {
      "kind": "line",
      "text": "So as long as they make the scenario interesting, they will have a chance."
    },
    {
      "kind": "line",
      "text": "\"Brother, the coins are…”"
    },
    {
      "kind": "line",
      "text": "\"I’ve collected enough.\""
    },
    {
      "kind": "line",
      "text": "\"Take mine too.\""
    },
    {
      "kind": "line",
      "text": "To defeat Yoo Joonghyuk in 'The Last Qualification', you must use the method that Kim Dokja used."
    },
    {
      "kind": "line",
      "text": "And that method required a huge amount of coins."
    },
    {
      "kind": "line",
      "text": "Lee Dansu, who was watching the scene, asked."
    },
    {
      "kind": "line",
      "text": "\"Isn’t Yerin the king?\""
    },
    {
      "kind": "line",
      "text": "\"Yes.\""
    },
    {
      "kind": "line",
      "text": "\"Then...\""
    },
    {
      "kind": "line",
      "text": "Killer King, who received Ja Yerin's gaze, responded."
    },
    {
      "kind": "line",
      "text": "\"I am the king.\""
    },
    {
      "kind": "line",
      "text": "\"Is that so.\""
    },
    {
      "kind": "line",
      "text": "\"Immortal King. Are you curious about what kind of king I am?\""
    },
    {
      "kind": "line",
      "text": "\"Yes?\""
    },
    {
      "kind": "line",
      "text": "Lee Dansu asked back blankly. He didn't know what to say, so he just muttered, but Killer King answered as he pleased."
    },
    {
      "kind": "line",
      "text": "\"I am the 'Lonely King'.\""
    },
    {
      "kind": "line",
      "text": "\"Lonely...\""
    },
    {
      "kind": "line",
      "text": "Lee Dansu wondered if he had heard wrong. Come to think of it, when he was choosing the 'King Options', he remembered seeing an option with that name."
    },
    {
      "kind": "line",
      "text": "But he didn't know that there would be someone who would bother to choose a name like that."
    },
    {
      "kind": "line",
      "text": "[The constellation 'Sneaky Schemer' shakes his head.]"
    },
    {
      "kind": "line",
      "text": "Even Ja Yerin secretly turned her head."
    },
    {
      "kind": "line",
      "text": "Killer King continued speaking with a shameless expression, as if he did not really understand such a reaction."
    },
    {
      "kind": "line",
      "text": "\"If you include you, me, and Ye Hyunwoo outside, there are a total of three 'kings' who can attend the final stage. It would have been better if Cheon Inho was also here.\""
    },
    {
      "kind": "line",
      "text": "Cheon Inho, who fell to the floor, showed no signs of regaining consciousness."
    },
    {
      "kind": "line",
      "text": "In fact, just being alive was a miracle."
    },
    {
      "kind": "line",
      "text": "\"For now, we have no choice but to try it on our own.\""
    },
    {
      "kind": "line",
      "text": "[Qualified kings move to the final battlefield’s location.]"
    },
    {
      "kind": "line",
      "text": "That's right. The summoning was beginning with a sound."
    },
    {
      "kind": "line",
      "text": "Sparks flew through the bodies of Killer King and Lee Dansu."
    },
    {
      "kind": "line",
      "text": "\"Yerin, please take care of Cheon Inho.\""
    },
    {
      "kind": "line",
      "text": "\"Don't worry.\""
    },
    {
      "kind": "line",
      "text": "Killer King looked back at the woman one last time. The woman was still reciting her spell with her hand placed on Cheon Inho's forehead. That spell seemed to be suppressing Cheon Inho’s [Madness]."
    },
    {
      "kind": "line",
      "text": "Killer King spoke to that woman."
    },
    {
      "kind": "line",
      "text": "\"7942.\""
    },
    {
      "kind": "line",
      "text": "Then the woman slowly opened her eyes and answered."
    },
    {
      "kind": "line",
      "text": "\"9158.\""
    },
    {
      "kind": "line",
      "text": "\"You remember it well.\""
    },
    {
      "kind": "line",
      "text": "\"Of course. This is the password I created.\""
    },
    {
      "kind": "line",
      "text": "Killer King nodded his head."
    },
    {
      "kind": "line",
      "text": "\"First Apostle, are you going to participate in the war?\""
    },
    {
      "kind": "line",
      "text": "Then the first apostle shook her head."
    },
    {
      "kind": "line",
      "text": "Killer King looked at the first apostle as if he was surprised, then turned his back and said."
    },
    {
      "kind": "line",
      "text": "\"When Cheon Inho wakes up, tell him. I will protect this world.\""
    },
    {
      "kind": "divider",
      "text": "---"
    },
    {
      "kind": "line",
      "text": "In my hazy consciousness, I had a dream."
    },
    {
      "kind": "quote",
      "text": "「\"Author, but…\"」"
    },
    {
      "kind": "line",
      "text": "I realized it the moment I heard the voice."
    },
    {
      "kind": "line",
      "text": "I see."
    },
    {
      "kind": "line",
      "text": "This is Ji Eunyu’s dream."
    },
    {
      "kind": "quote",
      "text": "「\"Yes.\"」"
    },
    {
      "kind": "line",
      "text": "The me in the dream answered."
    },
    {
      "kind": "line",
      "text": "I was afraid of what Ji Eunyu would say, and I was also looking forward to it."
    },
    {
      "kind": "quote",
      "text": "「\"In the last scene, Kim Dokja came back.\"」"
    },
    {
      "kind": "line",
      "text": "Last scene."
    },
    {
      "kind": "line",
      "text": "I immediately realized what Ji Eunyu was talking about."
    },
    {
      "kind": "line",
      "text": "The moment the door to the hospital room opens and Han Sooyoung and Yoo Joonghyuk return. At the moment when the readers who had become 'the oldest dream' were wishing for Kim Dokja's resurrection, Ji Eunyu was talking about that last scene."
    },
    {
      "kind": "line",
      "text": "I cautiously opened my mouth, looking around in case anyone heard me."
    },
    {
      "kind": "quote",
      "text": "「\"He’s back. You don't know that, it's an open ending.\"」"
    },
    {
      "kind": "line",
      "text": "Then Ji Eunyu frowned."
    },
    {
      "kind": "quote",
      "text": "「\"Do you really think so?\"」"
    },
    {
      "kind": "quote",
      "text": "「\"It has to be an open ending to increase the level of completion-\"」"
    },
    {
      "kind": "quote",
      "text": "「\"I don’t think the author has anything to say about the degree of completion.\"」"
    },
    {
      "kind": "line",
      "text": "I thought for a moment and then hesitated."
    },
    {
      "kind": "quote",
      "text": "「\"To leave a deep impression on readers, like a spinning top that seems to never stop...\"」"
    },
    {
      "kind": "quote",
      "text": "「\"Would you like to get your head stuck with a top?\"」"
    },
    {
      "kind": "line",
      "text": "I frowned as I watched Ji Eunyu’s fist spinning like a top."
    },
    {
      "kind": "quote",
      "text": "「\"I don't know. Han Sooyoung wrote it. Ask Han Sooyoung.\"」"
    },
    {
      "kind": "line",
      "text": "Ji Eunyu sighed lightly while looking at me and said."
    },
    {
      "kind": "quote",
      "text": "「\"Great. Let me ask you this. What if the author is the reader? What do you think when you see the last scene? Has Kim Dokja returned?\"」"
    },
    {
      "kind": "line",
      "text": "If I were a reader."
    },
    {
      "kind": "line",
      "text": "Actually, there is no need to ask that."
    },
    {
      "kind": "line",
      "text": "Because all the sentences in the last chapter refer to a single sentence that is not written down."
    },
    {
      "kind": "line",
      "text": "A puzzle with only one empty piece."
    },
    {
      "kind": "line",
      "text": "A unique non-existent sentence stands out more than any other sentence that exists."
    },
    {
      "kind": "quote",
      "text": "「\"Maybe he didn’t come back?\"」"
    },
    {
      "kind": "quote",
      "text": "「\"You will say that right away.\"」"
    },
    {
      "kind": "quote",
      "text": "「\"Don’t go somewhere else and say I did that.\"」"
    },
    {
      "kind": "quote",
      "text": "「\"Why did I do that? Rather, in what form did Kim Dokja return?\"」"
    },
    {
      "kind": "line",
      "text": "What shape is it?"
    },
    {
      "kind": "quote",
      "text": "「\"That’s the ending. There are countless Kim Dokjas scattered throughout the universe, and isn’t it because their wishes came true that Kim Dokja came back to life?\"」"
    },
    {
      "kind": "line",
      "text": "Hearing it from someone else's mouth, it somehow feels like the ending of a children's fairy tale."
    },
    {
      "kind": "quote",
      "text": "「\"I guess so?\"」"
    },
    {
      "kind": "quote",
      "text": "「\"Then there must have been Kim Dokjas who each had their own thoughts. What would happen if those readers thought at the same time, 'Dokja Kim is back'?\"」"
    },
    {
      "kind": "quote",
      "text": "「\"Uh...\"」"
    },
    {
      "kind": "line",
      "text": "I hadn't thought of that."
    },
    {
      "kind": "line",
      "text": "I felt scared for a moment and asked."
    },
    {
      "kind": "quote",
      "text": "「\"Maybe I should write it again?\"」"
    },
    {
      "kind": "line",
      "text": "The moment I blinked and thought, \"Please, I can’t do that,\" the scenery around me changed."
    },
    {
      "kind": "line",
      "text": "A ceiling blocked by a familiar stone wall."
    },
    {
      "kind": "line",
      "text": "The dimly shining light."
    },
    {
      "kind": "line",
      "text": "With the feeling of the floor, all the memories slowly came back."
    },
    {
      "kind": "line",
      "text": "Memories of entering the labyrinth to find the 'Death Sword'."
    },
    {
      "kind": "line",
      "text": "There, Killer King and others met Dansu ahjussi, absorbed the Star Jewels, a disaster was summoned, and the Labyrinth Watcher died..."
    },
    {
      "kind": "line",
      "text": "I almost died too."
    },
    {
      "kind": "line",
      "text": "As my thoughts reached that point, someone suddenly came to mind."
    },
    {
      "kind": "line",
      "text": "Ji Eunyu."
    },
    {
      "kind": "line",
      "text": "[Currently you have acquired a total of 6 Star Jewels.]"
    },
    {
      "kind": "line",
      "text": "[The power of the 'Star Jewel' erodes your body.]"
    },
    {
      "kind": "line",
      "text": "[The 6th level of madness is encroaching on you.]"
    },
    {
      "kind": "line",
      "text": "[An unknown force is suppressing your 'madness'.]"
    },
    {
      "kind": "line",
      "text": "[An unknown force is interfering with the erosion of the 'Star Jewels'.]"
    },
    {
      "kind": "line",
      "text": "I slowly got up. I felt a throbbing pain as if someone was squeezing my head."
    },
    {
      "kind": "line",
      "text": "There was no one around."
    },
    {
      "kind": "line",
      "text": "What happened?"
    },
    {
      "kind": "line",
      "text": "Clearly, the disaster and the watchman have fallen."
    },
    {
      "kind": "line",
      "text": "Where have the other party members gone?"
    },
    {
      "kind": "line",
      "text": "What happened to the scenario?"
    },
    {
      "kind": "line",
      "text": "[The owner of 'Absolute Throne' has been chosen.]"
    },
    {
      "kind": "line",
      "text": "At the momentary system message, I blinked blankly."
    },
    {
      "kind": "line",
      "text": "I thought I heard wrong."
    },
    {
      "kind": "line",
      "text": "'The owner of the absolute throne has been identified?'"
    },
    {
      "kind": "line",
      "text": "The information in my head was sorted in an instant."
    },
    {
      "kind": "line",
      "text": "The owner of the throne has been decided. That means the 'fight for the throne' has already begun and is over."
    },
    {
      "kind": "quote",
      "text": "「The fourth scenario has ended.」"
    },
    {
      "kind": "line",
      "text": "I looked at the small star gem rolling around on the floor."
    },
    {
      "kind": "line",
      "text": "I have six star gems. And there's one rolling around over there."
    },
    {
      "kind": "quote",
      "text": "「There is no Death Sword in this round.」"
    },
    {
      "kind": "line",
      "text": "My fingertips were shaking. Something that shouldn't have happened happened."
    },
    {
      "kind": "line",
      "text": "I felt the dungeon vibrating."
    },
    {
      "kind": "line",
      "text": "I felt sick. I knew it instinctively. Something sinister is about to be born in this world."
    },
    {
      "kind": "line",
      "text": "[The owner of the 'absolute throne' is...]"
    },
    {
      "kind": "line",
      "text": "A light came on in the distance and I heard someone running towards me."
    },
    {
      "kind": "line",
      "text": "[It is 'Incarnation Yoo Joonghyuk'.]"
    },
    {
      "kind": "line",
      "text": "The destruction of the 41st round was decided."
    }
  ],
  "authorNote": [],
  "sourceUrl": "epub:orv_sequel.epub#114",
  "scrapedAt": "2026-04-20T21:23:47.500Z"
}
