{
  "number": 628,
  "slug": "orv-seq-ch-628",
  "title": "628 Episode 15 Doorbell (1)",
  "order": 628,
  "segments": [
    {
      "kind": "quote",
      "text": "「Baekindohae No.89. 'The Mad Butcher'. Full name unknown. Age unknown. From Korea.」"
    },
    {
      "kind": "line",
      "text": "'The Mad Butcher' has been active in a variety of ways, from <The Devil's Tournament> to <Gigantomachia>. Some nebulae tried to recruit him several times, but it is known that he worked solo to the end, and disappeared in the 90's scenario."
    },
    {
      "kind": "line",
      "text": "His combat power, which entered the 'state of madness', competes for the top among incarnations, and there is also a record that he clashed with Ranbir Khan of India and engaged in a bloody battle when the giant tale <Mahanaraka> was opened."
    },
    {
      "kind": "line",
      "text": "The Mad Butcher, who haunts the scenarios like a ghost in search of the enemy who killed his comrades, always wore a 'skeleton mask'. It is said that no one knows the true face of the butcher behind the mask.」"
    },
    {
      "kind": "line",
      "text": "—Bicheonhori 『The 100 Strongest』"
    },
    {
      "kind": "divider",
      "text": "---"
    },
    {
      "kind": "line",
      "text": "We went straight to Seoul Station."
    },
    {
      "kind": "line",
      "text": "There were two main reasons."
    },
    {
      "kind": "line",
      "text": "One is to find the 'mad butcher' mentioned by Yoo Joonghyuk."
    },
    {
      "kind": "line",
      "text": "And the other."
    },
    {
      "kind": "line",
      "text": "[You are currently in the 'Wanderer' state.]"
    },
    {
      "kind": "line",
      "text": "[You must obtain a flag within the next two days.]"
    },
    {
      "kind": "line",
      "text": "Because it was the timing to acquire a new 'flag'."
    },
    {
      "kind": "line",
      "text": "If I wasn't going to participate in 'The Battle for the Throne', I would have maintained my status as a wanderer and searched for other ways to survive... But since this world was in the 41st turn, I had to prepare for it just in case."
    },
    {
      "kind": "line",
      "text": "Suddenly, Yoo Joonghyuk could do something strange, or strange guys like the Misreading Association could appear."
    },
    {
      "kind": "line",
      "text": "If they ever claim the 'absolute throne', this turn will be ruined."
    },
    {
      "kind": "line",
      "text": "\"Are you sure the butcher or something is in Seoul Station?\""
    },
    {
      "kind": "line",
      "text": "I nodded my head at Jung Heewon's question."
    },
    {
      "kind": "line",
      "text": "\"Yes. And there are probably hidden flags around here.\""
    },
    {
      "kind": "line",
      "text": "How did I know that?"
    },
    {
      "kind": "quote",
      "text": "「Near Seoul Station. There are hidden 'white flags' around Huamdong and Namyeongdong.」"
    },
    {
      "kind": "line",
      "text": "The moment I made up my mind to 'go to Seoul Station', the above sentence naturally came to my mind."
    },
    {
      "kind": "line",
      "text": "All of them were the effects of the newly acquired skill 'Ways of Survival'."
    },
    {
      "kind": "line",
      "text": "[Exclusive skill 'Three Ways to Survive in a Ruined World' is activated.]"
    },
    {
      "kind": "line",
      "text": "I hadn't figured out the exact way to use it yet."
    },
    {
      "kind": "line",
      "text": "I knew how to turn the skill on and off, but there was no function to find the content I wanted or to read a specific conversation of 'Ways of Survival'."
    },
    {
      "kind": "line",
      "text": "It was just that whenever I thought of something or did a certain action, a specific content of 'Ways of Survival' came to my mind like a game help. Of course, even that alone was a great help."
    },
    {
      "kind": "line",
      "text": "Seeing how I started to hear the sentences of 'Ways of Survival' right after I met Han Sooyoung, I wondered if Han Sooyoung had given me this skill."
    },
    {
      "kind": "line",
      "text": "But for what reason?"
    },
    {
      "kind": "line",
      "text": "I don't know."
    },
    {
      "kind": "line",
      "text": "What is certain is that I now have the information of 'Ways of Survival', and because of that, I have an overwhelming advantage over other readers and apostles."
    },
    {
      "kind": "line",
      "text": "That's it."
    },
    {
      "kind": "line",
      "text": "We quickly descended southwest to Seoul Station."
    },
    {
      "kind": "line",
      "text": "Foreigners can often be found when passing through Myeongdong, which is famous as a tourist destination."
    },
    {
      "kind": "line",
      "text": "It was not exactly foreigners, but the bodies of foreigners."
    },
    {
      "kind": "line",
      "text": "Most of the scattered corpses were devoured by lower monstrous species and couldn’t be recognized."
    },
    {
      "kind": "line",
      "text": "We walked, trying to avoid the scenery."
    },
    {
      "kind": "line",
      "text": "\"Wow, this street has changed like this. Have you been to Myeongdong often?\""
    },
    {
      "kind": "line",
      "text": "\"A few times when I was in college.\""
    },
    {
      "kind": "line",
      "text": "\"I used to work part-time at the theater over there.\""
    },
    {
      "kind": "line",
      "text": "Jung Heewon pointed to the half-collapsed building and said."
    },
    {
      "kind": "line",
      "text": "\"I'm sure there was...\""
    },
    {
      "kind": "line",
      "text": "In less than a month, Seoul as we knew it was now erased from the world."
    },
    {
      "kind": "line",
      "text": "As if a new story could only begin when that world collapsed."
    },
    {
      "kind": "line",
      "text": "\"This is where whirlwind potatoes were sold at a really high price. And lobsters.\""
    },
    {
      "kind": "line",
      "text": "\"Have you ever eaten them?\""
    },
    {
      "kind": "line",
      "text": "\"Never. How can you buy something so expensive?\""
    },
    {
      "kind": "line",
      "text": "Streets filled with stalls and crowds of merchants were now covered with corpses of monsters and humans."
    },
    {
      "kind": "line",
      "text": "\"It smelled good, though.\""
    },
    {
      "kind": "line",
      "text": "\"I know, right?\""
    },
    {
      "kind": "line",
      "text": "The Myeongdong that Jung Heewon remembers and the Myeongdong that I remember will be different."
    },
    {
      "kind": "line",
      "text": "But now we are standing together in the ruins of Myeongdong, yearning for the street food we thought we would never be able to buy and eat."
    },
    {
      "kind": "line",
      "text": "\"Inho-ssi.\""
    },
    {
      "kind": "line",
      "text": "\"Yes.\""
    },
    {
      "kind": "line",
      "text": "\"If you are going to Seoul Station, can I stop by Huamdong for a while? It's right nearby.\""
    },
    {
      "kind": "line",
      "text": "Huamdong."
    },
    {
      "kind": "line",
      "text": "According to 'Ways of Survival', there is a hidden place with a white flag there."
    },
    {
      "kind": "line",
      "text": "I nodded and asked."
    },
    {
      "kind": "line",
      "text": "\"Do you have anything to see there?\""
    },
    {
      "kind": "line",
      "text": "\"There's a place I'd like to stop by.\""
    },
    {
      "kind": "line",
      "text": "Places that survivors of the coveted world might want to visit."
    },
    {
      "kind": "line",
      "text": "I knew where it was without even asking."
    },
    {
      "kind": "divider",
      "text": "---"
    },
    {
      "kind": "line",
      "text": "The past history of Jung Heewon does not appear in 'Ways of Survival'. To be precise, even Jung Heewon is not mentioned. Because she wasn't the main character."
    },
    {
      "kind": "line",
      "text": "However, the past history of Jung Heewon was not properly dealt with even in 'Omniscient Reader', where she was a leading role in her own way."
    },
    {
      "kind": "line",
      "text": "Well, it wasn't just Jung Heewon."
    },
    {
      "kind": "line",
      "text": "The story of Lee Hyunsung's military service was not mentioned, the story of Lee Gilyoung's mother was omitted, the dead puppy of Shin Yoosoung was hidden, and the story of Lee Jihye's friend was minimally described."
    },
    {
      "kind": "line",
      "text": "After all, if it was Han Sooyoung who wrote this story, and <Kim Dokja's Company> was the one who told her story, then why aren't their stories introduced in Omniscient Reader’s Viewpoint?"
    },
    {
      "kind": "line",
      "text": "It wasn't hard to guess why."
    },
    {
      "kind": "line",
      "text": "Perhaps <Kim Dokja’s Company> is from Omniscient Reader’s Viewpoint."
    },
    {
      "kind": "line",
      "text": "Maybe they thought this wasn't their story."
    },
    {
      "kind": "line",
      "text": "After all, that story was Kim Dokja's story."
    },
    {
      "kind": "line",
      "text": "\"It’s here.\""
    },
    {
      "kind": "line",
      "text": "The place she guided me to was an apartment for a military unit facing a back alley."
    },
    {
      "kind": "line",
      "text": "\"How many years has it been? It's very old.\""
    },
    {
      "kind": "line",
      "text": "\"Did you come after a long time?\""
    },
    {
      "kind": "line",
      "text": "\"I left home when I was in high school. Didn't I tell you?\""
    },
    {
      "kind": "line",
      "text": "It may or may not have been heard."
    },
    {
      "kind": "line",
      "text": "\"Actually, I didn't want to come, but... I was on my way to Seoul Station.\""
    },
    {
      "kind": "line",
      "text": "Did someone remove the bodies? The entrance leading to the parking lot of the apartment was left with only bloodstains."
    },
    {
      "kind": "line",
      "text": "The apartment security room was smashed as if a monster had pushed it through. The windows on the veranda were broken as if they had been shelled."
    },
    {
      "kind": "line",
      "text": "Watching the curtains sway through the cracked glass, I thought about the things that had disappeared."
    },
    {
      "kind": "line",
      "text": "What happened to all the people who originally lived here?"
    },
    {
      "kind": "line",
      "text": "Did they also go through the first scenario? Had they gone through the first scenario, would they have killed their own family, or would they have knocked on the door next door and put a knife in the neighbor?"
    },
    {
      "kind": "line",
      "text": "I don't know what tragedy happened here."
    },
    {
      "kind": "line",
      "text": "I was afraid to find out."
    },
    {
      "kind": "quote",
      "text": "「There is a 'white flag' nearby.」"
    },
    {
      "kind": "line",
      "text": "But there is a white flag here, and we must take it. Yes, we will be able to buy tomorrow and the day after tomorrow."
    },
    {
      "kind": "line",
      "text": "We'll see the end of this damn world."
    },
    {
      "kind": "line",
      "text": "\"This is the house.\""
    },
    {
      "kind": "line",
      "text": "Jung Heewon's house was on the 5th floor of the apartment."
    },
    {
      "kind": "line",
      "text": "I said to Jung Heewon, who was giggling in front of the front door."
    },
    {
      "kind": "line",
      "text": "\"You don't have to go in.\""
    },
    {
      "kind": "line",
      "text": "She said she didn't like her family. But even such a family is, after all, a family."
    },
    {
      "kind": "line",
      "text": "\"Heewon-ssi has done enough to come this far.\""
    },
    {
      "kind": "line",
      "text": "Old-fashioned sense of duty and guilt. Somewhere in between, Jung Heewon had a lost expression."
    },
    {
      "kind": "line",
      "text": "Then, for an instant, a firm determination appeared on Jung Heewon's face."
    },
    {
      "kind": "line",
      "text": "\"I'll at least check.\""
    },
    {
      "kind": "line",
      "text": "She is also a strong person."
    },
    {
      "kind": "line",
      "text": "She knocked on the front door a few times and thought for a moment, then she raised the door lock cover and started typing her password."
    },
    {
      "kind": "line",
      "text": "Beep beep beep. Beep beep beep."
    },
    {
      "kind": "line",
      "text": "When it was wrong three times, the door opened."
    },
    {
      "kind": "line",
      "text": "\"It's still there.\""
    },
    {
      "kind": "line",
      "text": "As soon as she opened the door, I could feel the damp, stagnant air. The smell of a house that hasn't been ventilated for over a week."
    },
    {
      "kind": "line",
      "text": "Jung Heewon went inside without hesitation without taking off her shoes. She didn't ask who was there, she didn't even call their name."
    },
    {
      "kind": "line",
      "text": "I followed her, but after thinking about it for a while, I took off my shoes at her front door."
    },
    {
      "kind": "line",
      "text": "I took off my shoes next to other shoes, neatly arranged like a towel in a royal palace."
    },
    {
      "kind": "line",
      "text": "Sneakers were visible."
    },
    {
      "kind": "line",
      "text": "Probably no one is in this house. I had such a feeling."
    },
    {
      "kind": "line",
      "text": "Jung Heewon returned with a slightly relieved face, as if she had already looked around her house."
    },
    {
      "kind": "line",
      "text": "\"I don’t think you were both at home.\""
    },
    {
      "kind": "line",
      "text": "Was that fortunate or unfortunate?"
    },
    {
      "kind": "line",
      "text": "I do not know."
    },
    {
      "kind": "line",
      "text": "Perhaps Jung Heewon doesn't know either."
    },
    {
      "kind": "line",
      "text": "I don't know who the people who lived here were. However, it seemed that they were not the ones who cooked food at home."
    },
    {
      "kind": "line",
      "text": "I couldn't find food waste in the sink, and I didn't even see a garbage bag."
    },
    {
      "kind": "line",
      "text": "Jung Heewon stood at the living room window and looked out of her window for a moment."
    },
    {
      "kind": "line",
      "text": "\"You can see the apartment across the street. I lived there when I was young.\""
    },
    {
      "kind": "line",
      "text": "\"Then, I moved to a mountain village across the street. I've been to the front line, and I also lived in Yongsan for a while. Soldiers move apartments regularly.\""
    },
    {
      "kind": "line",
      "text": "Jung Heewon's father was a soldier."
    },
    {
      "kind": "line",
      "text": "When I was young, I had a friend who had a military father in Jingu, and I had heard a similar story."
    },
    {
      "kind": "line",
      "text": "\"When the place of dispatch changed, I moved to a new neighborhood, and my younger brother and I worked hard to follow my father. If we could adapt, he would move, and if we couldn’t adapt, he would move. After my mother ran away, the cycle accelerated.\""
    },
    {
      "kind": "line",
      "text": "Jung Heewon drew a circle on the foggy, dusty window."
    },
    {
      "kind": "line",
      "text": "\"Speaking of, the atmosphere of the neighborhoods is all similar. There is a military base nearby, and there is a unique refugee-like smell of families following soldiers. It is a site where soldiers live, so the government does not give expensive land. If it's Seoul, I wonder if there's a place like this in Seoul... That's why I left the house. I was so bored.\""
    },
    {
      "kind": "line",
      "text": "The circling finger stopped."
    },
    {
      "kind": "line",
      "text": "\"I'm tired of those people.\""
    },
    {
      "kind": "line",
      "text": "Jung Heewon slowly turned her head and looked around her."
    },
    {
      "kind": "line",
      "text": "Above the calf-length living room cabinet, I saw a framed family picture. In the photo, there was a middle-aged man in military uniform, a young Jung Heewon, and a boy who appeared to be her younger brother."
    },
    {
      "kind": "line",
      "text": "Seeing that he was wearing a graduation cap, it was probably a photo taken at the boy's primary school graduation ceremony."
    },
    {
      "kind": "line",
      "text": "Jung Heewon took out the picture in the frame."
    },
    {
      "kind": "line",
      "text": "\"But when I went out, society was the same.\""
    },
    {
      "kind": "line",
      "text": "Looking at that picture reminded me of my parents' faces."
    },
    {
      "kind": "line",
      "text": "My parents were good people."
    },
    {
      "kind": "line",
      "text": "They were really good people that I can't describe."
    },
    {
      "kind": "quote",
      "text": "「But Lee Hakhyun didn’t miss them that much.」"
    },
    {
      "kind": "line",
      "text": "I don't know why."
    },
    {
      "kind": "line",
      "text": "Is it because it's strange that I was born as the child of such good people, or..."
    },
    {
      "kind": "quote",
      "text": "「It must have been because I had the impression that it didn’t feel like my life.」"
    },
    {
      "kind": "line",
      "text": "It may be due to the influence of reading too many novels since childhood."
    },
    {
      "kind": "line",
      "text": "I always read books when I open my eyes, and I lived writing stories."
    },
    {
      "kind": "line",
      "text": "The place I've lived all along is the world inside the text."
    },
    {
      "kind": "line",
      "text": "It was a world of light and darkness ruled by dragons, swords, and magic."
    },
    {
      "kind": "quote",
      "text": "「Is that why? Lee Hakhyun has always lived his life with the feeling that he is living someone else's life instead.」"
    },
    {
      "kind": "line",
      "text": "Cheon Inho's narrow eyes were visible on the pitch-black screen of the TV, which was turned off."
    },
    {
      "kind": "line",
      "text": "A face that is not my face."
    },
    {
      "kind": "line",
      "text": "Even now I am living someone else's story."
    },
    {
      "kind": "line",
      "text": "[The constellation 'Demon-like Judge of Fire' looks at your face.]"
    },
    {
      "kind": "line",
      "text": "[Constellation 'The Prisoner of the Golden Headband' is curious about your thoughts.]"
    },
    {
      "kind": "line",
      "text": "[The constellation 'Abyssal Black Flame Dragon' warns you to stop doing nonsense and go kill other people.]"
    },
    {
      "kind": "line",
      "text": "I put my hand on my face reflected on the screen."
    },
    {
      "kind": "line",
      "text": "Was the Cheon Inho that I now possessed once someone's child?"
    },
    {
      "kind": "line",
      "text": "Was his family there?"
    },
    {
      "kind": "line",
      "text": "I first thought about the life of a villain who messed up the 40th turn and disappeared."
    },
    {
      "kind": "line",
      "text": "Where did Cheon Inho's original soul go?"
    },
    {
      "kind": "line",
      "text": "[The constellation 'Sneaky Schemer' feels sorry for you.]"
    },
    {
      "kind": "line",
      "text": "Jung Heewon finally raised her head."
    },
    {
      "kind": "line",
      "text": "\"That's okay. Let’s go now, because this is not our purpose for coming here.\""
    },
    {
      "kind": "line",
      "text": "I nodded."
    },
    {
      "kind": "line",
      "text": "Jung Heewon must have been listening to the message that was ringing in my ears from earlier."
    },
    {
      "kind": "line",
      "text": "[There is a 'white flag' hidden nearby.]"
    },
    {
      "kind": "line",
      "text": "[The closer you get to the location of the white flag, the shorter the message sending interval.]"
    },
    {
      "kind": "line",
      "text": "There is a 'white flag' somewhere in this apartment."
    },
    {
      "kind": "line",
      "text": "\"I don't think it’s at home.\""
    },
    {
      "kind": "line",
      "text": "First of all, it is not in Jung Heewon's house."
    },
    {
      "kind": "line",
      "text": "By measuring the dispatch interval of the message, it is possible to locate the flag."
    },
    {
      "kind": "line",
      "text": "At this close distance, the only place I could immediately suspect was... next door."
    },
    {
      "kind": "line",
      "text": "\"I think this is this house.\""
    },
    {
      "kind": "line",
      "text": "We stood at the old front door and looked at each other for a moment."
    },
    {
      "kind": "line",
      "text": "Jung Heewon asked first."
    },
    {
      "kind": "line",
      "text": "\"Should I ring the doorbell? Or should I break it?\""
    },
    {
      "kind": "line",
      "text": "\"If there were people inside, they would have captured the flag right away and this message wouldn't ring.\""
    },
    {
      "kind": "line",
      "text": "\"I see.\""
    },
    {
      "kind": "line",
      "text": "\"But just in case.\""
    },
    {
      "kind": "line",
      "text": "\"Which one is it?\""
    },
    {
      "kind": "line",
      "text": "We rang the doorbell of an empty house at the same time."
    },
    {
      "kind": "line",
      "text": "Of course, there was no reaction from people."
    },
    {
      "kind": "line",
      "text": "We thought together with a wry smile."
    },
    {
      "kind": "line",
      "text": "Still, isn't this the humanity we can find in this apocalypse?"
    },
    {
      "kind": "line",
      "text": "But the next moment."
    },
    {
      "kind": "line",
      "text": "Click."
    },
    {
      "kind": "line",
      "text": "Someone opened the door from the inside."
    }
  ],
  "authorNote": [],
  "sourceUrl": "epub:orv_sequel.epub#76",
  "scrapedAt": "2026-04-20T21:23:47.500Z"
}
