{
  "number": 880,
  "slug": "orv-seq-ch-880",
  "title": "880 Episode 48 Avatar (3)",
  "order": 880,
  "segments": [
    {
      "kind": "line",
      "text": "\"No, wait a minute.\""
    },
    {
      "kind": "line",
      "text": "It was unfair. Because it wasn’t me who left Han Sooyoung alone for the 1,863rd Round."
    },
    {
      "kind": "line",
      "text": "\"I’m not an [Avatar].\""
    },
    {
      "kind": "line",
      "text": "\"Then what?\""
    },
    {
      "kind": "line",
      "text": "\"I—\""
    },
    {
      "kind": "line",
      "text": "I hesitated. I couldn’t think of anything I could say to persuade her."
    },
    {
      "kind": "line",
      "text": "For a moment, a brief temptation occurred to me."
    },
    {
      "kind": "line",
      "text": "What if I just used [Incite]? If I used [Incite] to persuade Han Sooyoung to do my bidding."
    },
    {
      "kind": "line",
      "text": "\"I can hear your head spinning.\""
    },
    {
      "kind": "line",
      "text": "The moment I heard Han Sooyoung’s laughter, I realized. The opponent in front of me wasn’t someone who could do that."
    },
    {
      "kind": "line",
      "text": "There was nothing I could do. From here on out, I had no choice but to play fair."
    },
    {
      "kind": "line",
      "text": "\"Just as you’re not the avatar of 'Han Sooyoung in the 3rd Round', I’m not just Kim Dokja’s avatar.\""
    },
    {
      "kind": "line",
      "text": "Han Sooyoung smiled as if she found it interesting."
    },
    {
      "kind": "line",
      "text": "\"Really? How much of your memories did you inherit?\""
    },
    {
      "kind": "line",
      "text": "\"I barely received any memories.\""
    },
    {
      "kind": "line",
      "text": "\"Yeah. They call someone like you [Avatar]. But isn't that right?\""
    },
    {
      "kind": "line",
      "text": "\"Does the amount of memories you have matter? It's not the amount of memories that proves who I am.\""
    },
    {
      "kind": "line",
      "text": "\"Is that so?\""
    },
    {
      "kind": "line",
      "text": "Han Sooyoung nodded and wrote something in her notebook."
    },
    {
      "kind": "line",
      "text": "I added while looking at Han Sooyoung like that."
    },
    {
      "kind": "line",
      "text": "\"Just because Han Sooyoung did something wrong in the 3rd Round, you wouldn't blame her for it. It's a bit unfair to blame me for Kim Dokja's mistakes.\""
    },
    {
      "kind": "line",
      "text": "\"Are you trying to say that you're not that Kim Dokja?\""
    },
    {
      "kind": "line",
      "text": "\"Yes. I'm not the Kim Dokja you know.\""
    },
    {
      "kind": "line",
      "text": "\"Then there's no reason for me to help you? Because you're not that Kim Dokja.\""
    },
    {
      "kind": "line",
      "text": "Is that really the case? Damn it. I quickly changed my subject."
    },
    {
      "kind": "line",
      "text": "\"But there's something called joint responsibility in this world. Since I'm also using Kim Dokja's name, I think I'm qualified to atone for his mistakes.\""
    },
    {
      "kind": "line",
      "text": "Kim Dokja's joint responsibility."
    },
    {
      "kind": "line",
      "text": "It feels a bit unfair. If there is a responsibility for the Kim Dokja Solidarity, shouldn’t there also be benefits for the Kim Dokja Solidarity? But I’ve never received anything like that."
    },
    {
      "kind": "line",
      "text": "Of course, I couldn’t complain to Han Sooyoung right in front of me."
    },
    {
      "kind": "line",
      "text": "Han Sooyoung stared at me blankly and chuckled."
    },
    {
      "kind": "line",
      "text": "\"How are you going to atone for this?\""
    },
    {
      "kind": "line",
      "text": "I cleared my throat slightly and began to speak."
    },
    {
      "kind": "line",
      "text": "\"It’s all my fault. I’m sorry for leaving you alone. But I didn’t do it on purpose either.\""
    },
    {
      "kind": "line",
      "text": "Han Sooyoung’s eyes shook subtly. I didn’t miss that moment and continued to speak."
    },
    {
      "kind": "line",
      "text": "\"I was curious about your story too. I was curious about how you were doing, what you were thinking, and if something big had happened in your world.\""
    },
    {
      "kind": "line",
      "text": "\"…\""
    },
    {
      "kind": "line",
      "text": "\"I didn’t intentionally avoid visiting. I was just scared.\""
    },
    {
      "kind": "line",
      "text": "\"Are you scared?\""
    },
    {
      "kind": "line",
      "text": "\"Sometimes, when it’s a story you really like, it’s scary to know the ending.\""
    },
    {
      "kind": "line",
      "text": "Han Sooyoung quietly watched me like that, then glanced at Lee Seolhwa who was peeking at her from behind and smiled bitterly."
    },
    {
      "kind": "line",
      "text": "\"If someone saw me, they'd think I was doing this because I wanted an apology.\""
    },
    {
      "kind": "line",
      "text": "\"You weren't?\""
    },
    {
      "kind": "line",
      "text": "\"What would I do accepting something like that?\""
    },
    {
      "kind": "line",
      "text": "\"Then why are you upset?\""
    },
    {
      "kind": "line",
      "text": "Was that too direct? Han Sooyoung's expression cracked for a moment."
    },
    {
      "kind": "line",
      "text": "I didn't miss the opportunity and asked."
    },
    {
      "kind": "line",
      "text": "\"Do you by any chance like Kim Dokja?\""
    },
    {
      "kind": "line",
      "text": "\"What?\""
    },
    {
      "kind": "line",
      "text": "\"If that's not the case, there's no reason for you to be so upset. Weren't you and Kim Dokja just in a business relationship? You gave and took. You broke up cleanly.\""
    },
    {
      "kind": "line",
      "text": "\"…\""
    },
    {
      "kind": "line",
      "text": "\"Or did you actually want to go back to the 3rd Round with Kim Dokja?\""
    },
    {
      "kind": "line",
      "text": "Han Sooyoung belatedly asked with narrowed eyes."
    },
    {
      "kind": "line",
      "text": "\"You're talking about having a pierced mouth, but have you forgotten who's holding the knife?\""
    },
    {
      "kind": "line",
      "text": "\"I know. You’re holding on to it. And very tightly. So please spare me.\""
    },
    {
      "kind": "line",
      "text": "\"Oh my.\""
    },
    {
      "kind": "line",
      "text": "\"If you spare me, I’ll help you meet Kim Dokja.\""
    },
    {
      "kind": "line",
      "text": "Han Sooyoung paused for a moment and asked back."
    },
    {
      "kind": "line",
      "text": "\"Why do you think I want to meet that kid?\""
    },
    {
      "kind": "line",
      "text": "\"If not, I’m sorry, but that kid would really want to see you.\""
    },
    {
      "kind": "line",
      "text": "Han Sooyoung’s expression once again showed embarrassment."
    },
    {
      "kind": "line",
      "text": "\"If you keep talking nonsense…\""
    },
    {
      "kind": "line",
      "text": "\"Han Sooyoung.\""
    },
    {
      "kind": "line",
      "text": "Tsk tsk, sparks colored my incarnation body along with the sound. I decided to settle the matter before the aftermath grew any bigger."
    },
    {
      "kind": "line",
      "text": "\"Kim Dokja is in danger. Only you can save him.\""
    },
    {
      "kind": "line",
      "text": "Kim Dokja is in danger. I clearly saw the blue that spread across Han Sooyoung’s expression at those words. I was a little envious, and a little sorry."
    },
    {
      "kind": "line",
      "text": "\"Can you take responsibility for that statement?\""
    },
    {
      "kind": "line",
      "text": "\"Yes, I can take responsibility.\""
    },
    {
      "kind": "line",
      "text": "I knew how cowardly my words were."
    },
    {
      "kind": "line",
      "text": "Even if I didn’t do anything, she would meet Kim Dokja again. More precisely, the less I did anything, the higher the probability that she would meet Kim Dokja again."
    },
    {
      "kind": "line",
      "text": "She was destined to become tIs123, and she would definitely meet the young Kim Dokja."
    },
    {
      "kind": "line",
      "text": "Of course, it wouldn’t be the kind of reunion she wanted."
    },
    {
      "kind": "line",
      "text": "\"How is Kim Dokja in danger?\""
    },
    {
      "kind": "line",
      "text": "\"That is…\""
    },
    {
      "kind": "line",
      "text": "\"If I save you, you will tell me?\""
    },
    {
      "kind": "line",
      "text": "When I nodded, Han Sooyoung glared at me with a disapproving look and asked."
    },
    {
      "kind": "line",
      "text": "\"I need to know who you made a contract with to come here.\""
    },
    {
      "kind": "line",
      "text": "\"Will you help me?\""
    },
    {
      "kind": "line",
      "text": "\"I will listen to your story.\""
    },
    {
      "kind": "line",
      "text": "Fortunately, the atmosphere was not bad. I swallowed a light sigh and said."
    },
    {
      "kind": "line",
      "text": "\"I didn’t make a contract with anyone.\""
    },
    {
      "kind": "line",
      "text": "\"What?\""
    },
    {
      "kind": "line",
      "text": "\"I didn’t make an 'Otherworldly Covenant' to come here.\""
    },
    {
      "kind": "line",
      "text": "There is a possibility that an 'Otherworldly Covenant' that I don't know about has been activated."
    },
    {
      "kind": "line",
      "text": "Strictly speaking, I came here through the 'Fear Realm', and the owner of the 'Fear Realm' was the 'King of Fear'."
    },
    {
      "kind": "line",
      "text": "The 'King of Fear' held numerous Outer Gods, so it would be safe to say that the 'Fear Realm' itself was an 'Otherworldly Covenant'."
    },
    {
      "kind": "line",
      "text": "However, the 'Fear Realm' has now been destroyed, and the 'King of Fear' has lost his power."
    },
    {
      "kind": "line",
      "text": "In other words, the 'contract' that sent me here has lost its effect. However, Han Sooyoung's expression upon hearing my words was strange."
    },
    {
      "kind": "line",
      "text": "\"Wait a minute, then you—\""
    },
    {
      "kind": "line",
      "text": "At that moment, thunder rang out from outside the window. Han Sooyoung's eyebrows furrowed and Lee Seolhwa opened the curtains by the window almost at the same time."
    },
    {
      "kind": "line",
      "text": "\"Captain, something is strange!\""
    },
    {
      "kind": "line",
      "text": "Lee Hyunsung's shout from outside. There was a huge portal swirling in the sky outside the window."
    },
    {
      "kind": "line",
      "text": "I and Han Sooyoung knew what it was."
    },
    {
      "kind": "quote",
      "text": "「Great Hall.」"
    },
    {
      "kind": "line",
      "text": "A passageway to another world was about to open in the vast expanse of sky. A tremendous feast could be felt beyond the hall."
    },
    {
      "kind": "line",
      "text": "Han Sooyoung glared at me with a frown."
    },
    {
      "kind": "line",
      "text": "\"What on earth have you done?\""
    },
    {
      "kind": "line",
      "text": "I looked up at the sky in confusion."
    },
    {
      "kind": "quote",
      "text": "「Even if it was the 1,863rd Round, there’s no way a 'God of Another World' would suddenly descend in the clear sky.」"
    },
    {
      "kind": "line",
      "text": "The scale of probability eventually shifted toward offsetting its weight."
    },
    {
      "kind": "line",
      "text": "If a God of Another World had appeared, it meant that there was a 'probability' that he would descend in this world line."
    },
    {
      "kind": "line",
      "text": "My heart sank."
    },
    {
      "kind": "quote",
      "text": "「It’s because of me.」"
    },
    {
      "kind": "line",
      "text": "Up until now, my existence had been protected by a 'scenario'."
    },
    {
      "kind": "line",
      "text": "[The Management Bureau does not accept your existence.]"
    },
    {
      "kind": "line",
      "text": "However, there was no scenario assigned to me in this worldline. In other words, the current me was an existence that was not needed in the 'scenario'."
    },
    {
      "kind": "line",
      "text": "Tsutsutsutsut!"
    },
    {
      "kind": "line",
      "text": "The spark that was immediately felt in my incarnation body was the proof."
    },
    {
      "kind": "line",
      "text": "This worldline does not consider my existence 'probable'. Therefore, in order to protect the probability of this world, my existence must disappear."
    },
    {
      "kind": "line",
      "text": "【Ooooooooooo.】"
    },
    {
      "kind": "line",
      "text": "Therefore, the guy coming over from the 'Great Hall' right now was a kind of grim reaper that came to erase me from this world."
    },
    {
      "kind": "line",
      "text": "【IwantitIwantitIwantitIwantitIwantitIwantitIwantitIwantitIwantitIwantitIwantitIwantitIwantitIwantitIwantitIwantitIwantitIwantitIwantitIwantitIwantitIwantitIwantitIwantitIwantitIwantitIwantit.】"
    },
    {
      "kind": "line",
      "text": "Han Sooyoung didn't panic and just flicked her fingers in the air."
    },
    {
      "kind": "line",
      "text": "['True Word Defense System' is activating!]"
    },
    {
      "kind": "line",
      "text": "I felt something like a transparent membrane surrounding the headquarters. Surprisingly, the defense barrier was withstanding the true words of that distant Outer Gazingod."
    },
    {
      "kind": "line",
      "text": "Kugugugugu."
    },
    {
      "kind": "line",
      "text": "But as the size of the 'Great Hall' growing in the sky grew, the shaking of the defense barrier also increased."
    },
    {
      "kind": "line",
      "text": "Han Sooyoung glared at me and asked."
    },
    {
      "kind": "line",
      "text": "\"Do you know what you did?\""
    },
    {
      "kind": "line",
      "text": "\"I'm sorry.\""
    },
    {
      "kind": "line",
      "text": "\"You're apologizing for bringing something like that? Lee Seolhwa, did you finish measuring its level?\""
    },
    {
      "kind": "line",
      "text": "Lee Seolhwa, who was waiting nearby, shook her head and answered."
    },
    {
      "kind": "line",
      "text": "\"The story measuring device is broken.\""
    },
    {
      "kind": "line",
      "text": "\"It was fine until the last time you measured the 'Dream Eater', right?\""
    },
    {
      "kind": "line",
      "text": "\"It's level is higher than that time.\""
    },
    {
      "kind": "line",
      "text": "\"Then it's at least 'Old Being' level or higher. What's its true name?\""
    },
    {
      "kind": "line",
      "text": "\"I didn't figure it out.\""
    },
    {
      "kind": "line",
      "text": "\"Hmm.\""
    },
    {
      "kind": "line",
      "text": "Han Sooyoung's expression became very serious."
    },
    {
      "kind": "line",
      "text": "\"The Final Scenario is right around the corner, and because of this kid, the Earth could be destroyed.\""
    },
    {
      "kind": "line",
      "text": "I nodded calmly and said."
    },
    {
      "kind": "line",
      "text": "\"I'm really sorry. So please help me, Han Sooyoung.\""
    },
    {
      "kind": "line",
      "text": "Han Sooyoung grumbled as if she was dumbfounded by my words."
    },
    {
      "kind": "line",
      "text": "\"This is really shameless.\""
    },
    {
      "kind": "line",
      "text": "\"You don't have a choice anyway. If you don't help me, your worldline will be destroyed.\""
    },
    {
      "kind": "line",
      "text": "\"What do you want me to help you with?\""
    },
    {
      "kind": "line",
      "text": "\"Please help me return to the 41st Round.\""
    },
    {
      "kind": "line",
      "text": "As I said before, there are several conditions needed to 'move worldlines' in this world. However, I wasn't Yoo Joonghyuk, and I didn't have an 'ark' to cross worldlines like the Constellations."
    },
    {
      "kind": "line",
      "text": "So now, the only thing left for me is the last method."
    },
    {
      "kind": "line",
      "text": "\"I will make an Otherworldly Covenant.\""
    },
    {
      "kind": "line",
      "text": "\"Will that work now?\""
    },
    {
      "kind": "line",
      "text": "\"Why not?\""
    },
    {
      "kind": "line",
      "text": "\"With that kind of thing targeting you right now, do you think there would be an Outer God that wants to make an 'Otherwordly Covenant' with you?\""
    },
    {
      "kind": "line",
      "text": "Han Sooyoung was right."
    },
    {
      "kind": "line",
      "text": "The otherworldly deity that is making an 'Otherworldly Covenant' right now will definitely clash with the Outer God targeting me from beyond the 'Great Hall'."
    },
    {
      "kind": "line",
      "text": "In other words, only a being stronger than the 'Outer God' targeting me would accept my offer."
    },
    {
      "kind": "line",
      "text": "\"If the guy over there is stronger than the 'Old Being', then there is a possibility that he is at the level of the 'Great Old Being'.\""
    },
    {
      "kind": "line",
      "text": "Great Old Being."
    },
    {
      "kind": "line",
      "text": "I kept my mouth shut at that expression that I had finally heard. Han Sooyoung added, how she had taken my silence unknown."
    },
    {
      "kind": "line",
      "text": "\"If the guy over there is at the 'Great Old Being' level, then there will be no Outer God that will help you.\""
    },
    {
      "kind": "line",
      "text": "I knew it too."
    },
    {
      "kind": "line",
      "text": "The Outer God that reaches the 'Great Old Being' level is a kind of 'Mythical Constellation' among the Outer Gods."
    },
    {
      "kind": "line",
      "text": "Still, I shook my head."
    },
    {
      "kind": "line",
      "text": "\"No, it's not like there's no one.\""
    },
    {
      "kind": "line",
      "text": "Even if the being that covets me from beyond is a 'Great Old Being', it's not like there's no Outer God that can stand against it."
    },
    {
      "kind": "line",
      "text": "\"You, really.\""
    },
    {
      "kind": "line",
      "text": "Han Sooyoung's expression as she looked at me was strangely hardened. Perhaps she had realized it too."
    },
    {
      "kind": "line",
      "text": "\"The being that brought you to this 'worldline'.\""
    },
    {
      "kind": "line",
      "text": "The only being that can stand against a 'Great Old Being' is a 'Great Old Being'."
    },
    {
      "kind": "line",
      "text": "I took a deep breath and opened my mouth."
    },
    {
      "kind": "line",
      "text": "\"Han Sooyoung, please call 'Secretive Plotter'.\""
    }
  ],
  "authorNote": [],
  "sourceUrl": "epub:orv_sequel.epub#328",
  "scrapedAt": "2026-04-20T21:23:47.500Z"
}
